dualopt/__init__.py
dualopt/classification.py
dualopt-0.1.8.dist-info/LICENSE
dualopt-0.1.8.dist-info/METADATA
dualopt-0.1.8.dist-info/WHEEL
dualopt-0.1.8.dist-info/top_level.txt
dualopt-0.1.8.dist-info/RECORD
