Metadata-Version: 2.1
Name: dualopt
Version: 0.1.8
Summary: Dual Optimizer Training
Home-page: https://github.com/pranavphoenix/DualOpt
Author: Pranav Jeevan
Author-email: pranav13phoenix@gmail.com
License: MIT
Keywords: artificial intelligence,machine learning,optimizer,training,image classificationsemantic segmentation,image super-resolution
Classifier: Development Status :: 4 - Beta
Classifier: Intended Audience :: Developers
Classifier: Topic :: Scientific/Engineering :: Artificial Intelligence
Classifier: License :: OSI Approved :: MIT License
Classifier: Programming Language :: Python :: 3.6
License-File: LICENSE
Requires-Dist: torch
Requires-Dist: torchvision
Requires-Dist: torchmetrics
Requires-Dist: numpy
Requires-Dist: lion-pytorch
